haystack/__init__.py
haystack/argparse_utils.py
haystack/basicmodel.py
haystack/cli.py
haystack/cliwin.py
haystack/constraints.py
haystack/dbg.py
haystack/listmodel.py
haystack/memory_dumper.py
haystack/model.py
haystack/target.py
haystack/types.py
haystack/utils.py
haystack/win-dump-heap.py
haystack/abc/__init__.py
haystack/abc/interfaces.py
haystack/allocators/__init__.py
haystack/allocators/heapwalker.py
haystack/allocators/libc/__init__.py
haystack/allocators/libc/ctypes_elf.py
haystack/allocators/libc/ctypes_malloc.py
haystack/allocators/libc/libcheap.constraints
haystack/allocators/libc/libcheapwalker.py
haystack/allocators/libc/libdl.py
haystack/allocators/libc/sandbox.py
haystack/allocators/win32/__init__.py
haystack/allocators/win32/win7_32.py
haystack/allocators/win32/win7_64.py
haystack/allocators/win32/win7heap.py
haystack/allocators/win32/win7heap32.constraints
haystack/allocators/win32/win7heap64.constraints
haystack/allocators/win32/win7heapwalker.py
haystack/allocators/win32/winheap.py
haystack/allocators/win32/winheapwalker.py
haystack/allocators/win32/winxp_32.py
haystack/allocators/win32/winxp_32_peb.py
haystack/allocators/win32/winxp_64.py
haystack/allocators/win32/winxpheap.py
haystack/allocators/win32/winxpheap32.constraints
haystack/allocators/win32/winxpheap64.constraints
haystack/allocators/win32/winxpheapwalker.py
haystack/mappings/__init__.py
haystack/mappings/base.py
haystack/mappings/cuckoo.py
haystack/mappings/file.py
haystack/mappings/folder.py
haystack/mappings/fridaprocess.py
haystack/mappings/minidump.py
haystack/mappings/process.py
haystack/mappings/rek.py
haystack/mappings/vol.py
haystack/mappings/vol2map.py
haystack/outputters/__init__.py
haystack/outputters/python.py
haystack/outputters/text.py
haystack/search/__init__.py
haystack/search/api.py
haystack/search/searcher.py
haystack-0.42.dist-info/DESCRIPTION.rst
haystack-0.42.dist-info/METADATA
haystack-0.42.dist-info/RECORD
haystack-0.42.dist-info/WHEEL
haystack-0.42.dist-info/dependency_links.txt
haystack-0.42.dist-info/entry_points.txt
haystack-0.42.dist-info/metadata.json
haystack-0.42.dist-info/top_level.txt
