Metadata-Version: 1.1
Name: haystack
Version: 0.42
Summary: Search C Structures in a process' memory
Home-page: http://packages.python.org/haystack/
Author: Loic Jaquemet
Author-email: loic.jaquemet+python@gmail.com
License: GPL
Download-URL: http://github.com/trolldbois/python-haystack/tree/master
Keywords: memory,analysis,forensics,record,struct,ptrace,heap,lfh,lal
Platform: UNKNOWN
Classifier: Topic :: System :: Networking
Classifier: Topic :: Security
Classifier: Environment :: Console
Classifier: Intended Audience :: Developers
Classifier: License :: OSI Approved :: GNU General Public License (GPL)
Classifier: Programming Language :: Python
Classifier: Development Status :: 4 - Beta
